fl_client/__init__.py
fl_client/auth.py
fl_client/cli.py
fl_client/evaluate.py
fl_client/model.py
fl_client/setup.py
fl_client/supabase_config.py
fl_client/sync.py
fl_client/train.py
fl_client/config/firebase_config.example.json
fl_client/config/supabase_config.example.json
fl_client/data/sample_diabetes_client1.csv
fl_client/data/sample_diabetes_test.csv
fl_healthcare_client-0.2.0.dist-info/licenses/LICENSE
fl_healthcare_client-0.2.0.dist-info/METADATA
fl_healthcare_client-0.2.0.dist-info/WHEEL
fl_healthcare_client-0.2.0.dist-info/entry_points.txt
fl_healthcare_client-0.2.0.dist-info/top_level.txt
fl_healthcare_client-0.2.0.dist-info/RECORD
