Metadata-Version: 2.4
Name: fl-healthcare-client
Version: 0.2.0
Summary: A self-contained CLI tool for federated learning with healthcare data - works out of the box without external service setup
Author-email: Znaxh <znaxh@gmail.com>
Maintainer-email: Znaxh <znaxh@gmail.com>
License: MIT
Project-URL: Homepage, https://github.com/yourusername/federated-learning-client
Project-URL: Documentation, https://github.com/yourusername/federated-learning-client#readme
Project-URL: Repository, https://github.com/yourusername/federated-learning-client
Project-URL: Bug Tracker, https://github.com/yourusername/federated-learning-client/issues
Keywords: federated-learning,machine-learning,healthcare,cli,privacy
Classifier: Development Status :: 3 - Alpha
Classifier: Intended Audience :: Developers
Classifier: Intended Audience :: Healthcare Industry
Classifier: Intended Audience :: Science/Research
Classifier: License :: OSI Approved :: MIT License
Classifier: Operating System :: OS Independent
Classifier: Programming Language :: Python :: 3
Classifier: Programming Language :: Python :: 3.8
Classifier: Programming Language :: Python :: 3.9
Classifier: Programming Language :: Python :: 3.10
Classifier: Programming Language :: Python :: 3.11
Classifier: Programming Language :: Python :: 3.12
Classifier: Topic :: Scientific/Engineering :: Artificial Intelligence
Classifier: Topic :: Software Development :: Libraries :: Python Modules
Requires-Python: >=3.8
License-File: LICENSE
Requires-Dist: typer>=0.9.0
Requires-Dist: pandas>=2.0.0
Requires-Dist: scikit-learn>=1.3.0
Requires-Dist: rich>=13.0.0
Requires-Dist: requests>=2.28.0
Requires-Dist: numpy>=1.24.0
Requires-Dist: joblib>=1.3.0
Provides-Extra: dev
Requires-Dist: pytest>=7.0.0; extra == "dev"
Requires-Dist: pytest-cov>=4.0.0; extra == "dev"
Requires-Dist: black>=23.0.0; extra == "dev"
Requires-Dist: flake8>=6.0.0; extra == "dev"
Requires-Dist: mypy>=1.0.0; extra == "dev"
Provides-Extra: external-services
Requires-Dist: supabase>=2.0.0; extra == "external-services"
Requires-Dist: firebase-admin>=6.0.0; extra == "external-services"
Requires-Dist: python-dotenv>=1.0.0; extra == "external-services"
Dynamic: license-file
